lx/__init__.py
lx/__main__.py
lx/__version__.py
lx/batch.py
lx/conf_search.py
lx/ld.py
lx/omega.py
lx/parser.py
lx/tools.py
LeoX-0.9.0.dist-info/LICENSE
LeoX-0.9.0.dist-info/METADATA
LeoX-0.9.0.dist-info/WHEEL
LeoX-0.9.0.dist-info/entry_points.txt
LeoX-0.9.0.dist-info/top_level.txt
LeoX-0.9.0.dist-info/RECORD
