Metadata-Version: 2.1
Name: LeoX
Version: 0.9.0
Summary: Spectrum simulations with TD(A)-DFT
Home-page: https://github.com/LeonardoESousa/LeoX
Author: Leonardo Evaristo de Sousa
Author-email: leonardo.sousa137@gmail.com
License: MIT
Classifier: License :: OSI Approved :: MIT License
Classifier: Programming Language :: Python
Classifier: Programming Language :: Python :: 3
Requires-Python: >=3.6.0
License-File: LICENSE
Requires-Dist: numpy
Requires-Dist: scipy
Requires-Dist: pandas
Requires-Dist: wheel
Requires-Dist: requests
Requires-Dist: joblib
